{

  "Stairs":
  [
    {
      "Sound": "12_Days_of_Christmas_Instrumental.mp3",
      "Day": "12 days of christmas Instruments"

    },

   {
     "Sound": "12_Days_of_Christmas_Vocals.mp3",
       "Day": "12 days of christmas"

   },

   {
     "Sound": "Dance_Of_The_Sugar_Plum_Fairies_by_Tchaikovsky.mp3",
      "Day": "dance of the sugar plum fairies"

   },
{

    "Sound": "Deck_the_Halls_Vocals.mp3",
     "Day": "deck the halls"


},

{

    "Sound": "Deck_the_Halls_Instrumental.mp3",
     "Day": "Deck the Halls Instruments"


},

{

    "Sound": "Deck_the_Halls_Jazz.mp3",
     "Day": "Deck the Halls jazz"


},

{

    "Sound": "First_Noel_Vocals.mp3",
     "Day": "First Noel Vocals"


},

{

    "Sound": "First_Noel_Instrumental.mp3",
     "Day": "First Noel Instruments"


},

{

    "Sound": "Jingle_Bells_Instrumental.mp3",
     "Day": "jingle bells Instruments"


},

{

    "Sound": "Nemesis.mp3",
     "Day": "Nemesis"


},

{

    "Sound": "O_Christmas_Tree.mp3",
     "Day": "oh christmas tree"


},

{

    "Sound": "Hark_the_Herald_Angels_Sing_Vocals.mp3",
     "Day": "Hark the Herald Angels Sing"


},
{

    "Sound": "Hark_the_Herald_Angels_Sing_Instrumental.mp3",
     "Day": "Hark the Herald Angels Sing Instruments"


},
{

    "Sound": "Holiday_Brass_Ensemble.mp3",
     "Day": "Holiday Brass Ensemble"


},

{

    "Sound": "Jolly_Old_St_Nicholas.mp3",
     "Day": "Jolly Old St Nicholas"


},

{

    "Sound": "Christmas_Homecoming.mp3",
     "Day": "Christmas Homecoming"


},
{

    "Sound": "Up_on_the_Housetop.mp3",
     "Day": "Up on the Housetop"


},

{

    "Sound": "Up_on_the_Housetop_Instrumental.mp3",
     "Day": "Up on the Housetop Instruments"


},
{

    "Sound": "Prizefighter.mp3",
     "Day": "Prizefighter"


},

{

    "Sound": "Silent_Night_Jazz.mp3",
     "Day": "Silent Night jazz"


},

{

    "Sound": "Silent_Night_Vocals.mp3",
     "Day": "Silent Night"


},

{

    "Sound": "Silent_Night_Instrumental.mp3",
     "Day": "Silent Night Instruments"


},

{

    "Sound": "Joy_to_the_World.mp3",
     "Day": "Joy to the World"


},

{

    "Sound": "Joy_to_the_World_Instrumental.mp3",
     "Day": "Joy to the World Instruments"


},

{

    "Sound": "Joy_to_the_World_Jazz.mp3",
     "Day": "Joy to the World jazz"


},

{

    "Sound": "Waltz_of_the_Flowers_by_Tchaikovsky.mp3",
     "Day": "Waltz of the Flowers"


},

{

    "Sound": "Oh_Little_Town_of_Bethlehem.mp3",
     "Day": "Little Town of Bethlehem"


},
{

    "Sound": "Jingle_Bells_Vocals.mp3",
     "Day": "Jingle Bells"


},

{

    "Sound": "Jingle_Bells_Jazz.mp3",
     "Day": "Jingle Bells Jazz"


},
{

    "Sound": "We_Wish_You_a_Merry_Christmas_Vocals.mp3",
     "Day": "We Wish You a Merry Christmas"


},

{

    "Sound": "We_Wish_You_a_Merry_Christmas_Instrumental.mp3",
     "Day": "We Wish You a Merry Christmas Instruments"


},

{

    "Sound": "We_Wish_You_a_Merry_Christmas_Instrumental_Jazz.mp3",
     "Day": "We Wish You a Merry Christmas jazz"


},

{

    "Sound": "O_Come_All_Ye_Faithful_Vocals.mp3",
     "Day": "Oh Come All Ye Faithful"


},
{

    "Sound": "O_Come_All_Ye_Faithful_Instrumental.mp3",
     "Day": "Oh Come All Ye Faithful Instruments"


},
{

    "Sound": "O_Come_All_Ye_Faithful_Instrumental.mp3",
     "Day": "Oh Come All Ye Faithful Instruments"


}
























  ]
}
